Workbook

Sheet Rent Roll
A1: Tenant | B1: Area (sqft) | C1: Base Rent per sqft (₹/month) | D1: Lease Start | E1: Lease End | F1: Escalation %
A2: Tenant A | B2: 1000 | C2: 50 | D2: Jan-2025 | E2: Dec-2029 | F2: 5%
A3: Tenant B | B3: 800 | C3: 55 | D3: Jan-2025 | E3: Dec-2029 | F3: 5%
A4: Tenant C | B4: 1200 | C4: 48 | D4: Jan-2025 | E4: Dec-2029 | F4: 5%

Sheet Operating Expenses
A1: Expense Category | B1: Annual Amount (₹)
A2: Maintenance | B2: 80000
A3: Utilities | B3: 50000
A4: Property Tax | B4: 120000
A5: Security & Cleaning | B5: 60000
A6: Insurance | B6: 40000
A7: Total Expenses | B7: =SUM(B2:B6)

Sheet Cash Flow
A1: Year | B1: Gross Rent | C1: Vacancy Rate | D1: Effective Rent | E1: Operating Expenses | F1: NOI | G1: Cap Rate | H1: Property Value
A2: Year 1 | B2: =('Rent Roll'!B2*'Rent Roll'!C2*12)+('Rent Roll'!B3*'Rent Roll'!C3*12)+('Rent Roll'!B4*'Rent Roll'!C4*12) | C2: 0.05 | D2: =B2*(1-C2) | E2: ='Operating Expenses'!B7 | F2: =D2-E2 | G2: 0.08 | H2: =F2/G2
A3: Year 2 | B3: =B2*1.05 | C3: 0.05 | D3: =B3*(1-C3) | E3: ='Operating Expenses'!B7 | F3: =D3-E3 | G3: 0.08 | H3: =F3/G3
A4: Year 3 | B4: =B3*1.05 | C4: 0.05 | D4: =B4*(1-C4) | E4: ='Operating Expenses'!B7 | F4: =D4-E4 | G4: 0.08 | H4: =F4/G4
A5: Year 4 | B5: =B4*1.05 | C5: 0.05 | D5: =B5*(1-C5) | E5: ='Operating Expenses'!B7 | F5: =D5-E5 | G5: 0.08 | H5: =F5/G5
A6: Year 5 | B6: =B5*1.05 | C6: 0.05 | D6: =B6*(1-C6) | E6: ='Operating Expenses'!B7 | F6: =D6-E6 | G6: 0.08 | H6: =F6/G6

Sheet Sensitivity
A1: Cap Rate | B1: NOI (Y1) | C1: Value
A2: 0.07 | B2: ='Cash Flow'!F2 | C2: =B2/A2
A3: 0.08 | B3: ='Cash Flow'!F2 | C3: =B3/A3
A4: 0.09 | B4: ='Cash Flow'!F2 | C4: =B4/A4
